flashinfer/__init__.py
test_flashinfer-0.0.1.dist-info/METADATA
test_flashinfer-0.0.1.dist-info/WHEEL
test_flashinfer-0.0.1.dist-info/top_level.txt
test_flashinfer-0.0.1.dist-info/RECORD
