Metadata-Version: 2.4
Name: test-flashinfer
Version: 0.0.1
Summary: Fast Attention Algorithms for LLM Inference
Author-email: AMD <support@amd.com>
License: Apache-2.0
Requires-Python: >=3.8
